grafq/__init__.py
grafq/client.py
grafq/errors.py
grafq/language.py
grafq/schema.py
grafq-0.0.3.dist-info/LICENSE
grafq-0.0.3.dist-info/METADATA
grafq-0.0.3.dist-info/WHEEL
grafq-0.0.3.dist-info/top_level.txt
grafq-0.0.3.dist-info/RECORD
