Metadata-Version: 2.1
Name: grafq
Version: 0.0.3
Summary: A pythonic way to build GraphQL queries
Home-page: https://github.com/asmello/grafq
Author: André Sá de Mello
Author-email: asmello.br@gmail.com
License: MIT
Project-URL: Bug Tracker, https://github.com/asmello/grafq/issues
Keywords: graphql
Platform: UNKNOWN
Classifier: Programming Language :: Python :: 3
Classifier: License :: OSI Approved :: MIT License
Classifier: Operating System :: OS Independent
Requires-Python: >=3.9
License-File: LICENSE
Requires-Dist: requests
